pyaota/__init__.py
pyaota/cli.py
pyaota/data/models/mnist_digit_cnn.keras
pyaota/generator/__init__.py
pyaota/generator/answersheet.py
pyaota/generator/document.py
pyaota/generator/layout_config_serialization.py
pyaota/generator/manager.py
pyaota/generator/questionset.py
pyaota/generator/wordexport2rawyaml.py
pyaota/generator/yaml2tex.py
pyaota/grader/__init__.py
pyaota/grader/answersheetreader.py
pyaota/grader/autograder.py
pyaota/latex/__init__.py
pyaota/latex/content.py
pyaota/latex/latexcompiler.py
pyaota/ocr/__init__.py
pyaota/ocr/digit_ocr.py
pyaota/ocr/train_mnist_digit_model.py
pyaota/util/__init__.py
pyaota/util/collectors.py
pyaota/util/command.py
pyaota/util/text.py
pyaota-0.2.0.dist-info/METADATA
pyaota-0.2.0.dist-info/WHEEL
pyaota-0.2.0.dist-info/entry_points.txt
pyaota-0.2.0.dist-info/licenses/LICENSE
pyaota-0.2.0.dist-info/RECORD
