Metadata-Version: 2.4
Name: pyaota
Version: 0.2.0
Summary: Python app for generating and grading exams.
Author: Cameron F. Abrams
License: MIT License
License-File: LICENSE
Requires-Python: >=3.10
Requires-Dist: docx
Requires-Dist: numpy
Requires-Dist: opencv-python
Requires-Dist: pdf2image
Requires-Dist: pyyaml
Requires-Dist: tensorflow>=2.12
Provides-Extra: dev
Requires-Dist: black; extra == 'dev'
Requires-Dist: pytest; extra == 'dev'
Requires-Dist: pytest-cov; extra == 'dev'
Requires-Dist: ruff; extra == 'dev'
Provides-Extra: docs
Requires-Dist: furo; extra == 'docs'
Requires-Dist: myst-parser; extra == 'docs'
Requires-Dist: sphinx; extra == 'docs'
Requires-Dist: sphinx-autodoc-typehints; extra == 'docs'
